pprint3x/__init__.py
pprint3x/__init__conf__.py
pprint3x/pprint3x.py
pprint3x/pprint3x.pyi
pprint3x/py.typed
pprint3x-3.10.4.6.dist-info/LICENSE
pprint3x-3.10.4.6.dist-info/METADATA
pprint3x-3.10.4.6.dist-info/WHEEL
pprint3x-3.10.4.6.dist-info/top_level.txt
pprint3x-3.10.4.6.dist-info/RECORD
